namespacelib/__init__.py
namespacelib/_version.py
namespacelib/codemeta.py
namespacelib/core.py
namespacelib/m4i.py
namespacelib/obo.py
namespacelib/pivmeta.py
namespacelib/qudt_kind.py
namespacelib/qudt_unit.py
namespacelib/schema.py
namespacelib/ssno.py
namespacelib-0.4.0.dist-info/LICENSE
namespacelib-0.4.0.dist-info/METADATA
namespacelib-0.4.0.dist-info/WHEEL
namespacelib-0.4.0.dist-info/top_level.txt
namespacelib-0.4.0.dist-info/RECORD
