Metadata-Version: 2.1
Name: namespacelib
Version: 0.4.0
Summary: Utility library for the work with ontology namespaces.
Home-page: https://github.com/matthiasprobst/namespacelib
Author: Matthias Probst
Author-email: matthias.probst@kit.edu
Classifier: Programming Language :: Python :: 3.8
Classifier: Programming Language :: Python :: 3.9
Classifier: Programming Language :: Python :: 3.10
Classifier: Programming Language :: Python :: 3.11
Classifier: Programming Language :: Python :: 3.12
Classifier: License :: OSI Approved :: MIT License
Classifier: Operating System :: OS Independent
Classifier: Development Status :: 4 - Beta
Classifier: Topic :: Scientific/Engineering
Requires-Python: <3.13,>=3.8
License-File: LICENSE
Requires-Dist: rdflib
Provides-Extra: complete
Requires-Dist: pytest >=7.1.2 ; extra == 'complete'
Provides-Extra: test
Requires-Dist: pytest >=7.1.2 ; extra == 'test'
